MANIFEST.in
README.markdown
setup.py
ckanapi_exporter/__init__.py
ckanapi_exporter/exporter.py
ckanapi_exporter/test_exporter.py
ckanapi_exporter.egg-info/PKG-INFO
ckanapi_exporter.egg-info/SOURCES.txt
ckanapi_exporter.egg-info/dependency_links.txt
ckanapi_exporter.egg-info/entry_points.txt
ckanapi_exporter.egg-info/requires.txt
ckanapi_exporter.egg-info/top_level.txt