Metadata-Version: 1.1
Name: ckanapi-exporter
Version: 0.1.0
Summary: Export dataset metadata from CKAN to Excel
Home-page: https://github.com/ckan/ckanapi-exporter
Author: Sean Hammond
Author-email: ckanapi-exporter@seanh.cc
License: AGPL
Keywords: ckan csv export excel api
Platform: UNKNOWN
Classifier: Development Status :: 4 - Beta
Classifier: License :: OSI Approved :: GNU Affero General Public License v3 or later (AGPLv3+)
Classifier: Programming Language :: Python :: 2.7
